bdtk/__init__.py
bdtk/utils.py
bdtk-0.1.1.dist-info/LICENSE
bdtk-0.1.1.dist-info/METADATA
bdtk-0.1.1.dist-info/WHEEL
bdtk-0.1.1.dist-info/top_level.txt
bdtk-0.1.1.dist-info/RECORD
