Metadata-Version: 2.1
Name: bdtk
Version: 0.1.1
Summary: A small data analysis package
Home-page: https://github.com/aurumkathuria/BDToolkit
Author: Aurum Kathuria
Author-email: armkatspamblocker@gmail.com
License: UNKNOWN
Platform: UNKNOWN
Classifier: Programming Language :: Python :: 3
Classifier: License :: OSI Approved :: MIT License
Classifier: Operating System :: OS Independent
Requires-Python: >=3.6
Requires-Dist: pandas (>=0.25.1)
Requires-Dist: numpy (>=1.16.5)
Requires-Dist: seaborn (>=0.9.0)
Requires-Dist: matplotlib (>=3.1.1)
Requires-Dist: ipywidgets (>=7.5.1)
